verysimplemodule_marcos/__init__.py
verysimplemodule_marcos/add.py
verysimplemodule_marcos/subtract.py
verysimplemodule_marcos/extra/__init__.py
verysimplemodule_marcos/extra/divide.py
verysimplemodule_marcos/extra/multiple.py
verysimplemodule_marcos-0.0.1.dist-info/METADATA
verysimplemodule_marcos-0.0.1.dist-info/WHEEL
verysimplemodule_marcos-0.0.1.dist-info/top_level.txt
verysimplemodule_marcos-0.0.1.dist-info/RECORD
