Metadata-Version: 2.1
Name: verysimplemodule-marcos
Version: 0.0.1
Summary: Meu primeiro pacote
Author: Marcos
Author-email: marcosofc04@gmail.com
Keywords: python,primeiro pacote
Requires-Dist: scikit-image
Requires-Dist: numpy
